secureclientserverservice/__init__.py
secureclientserverservice/scssEchoClient.py
secureclientserverservice/scssEchoServer.py
secureclientserverservice/scssclient/ScssClient.py
secureclientserverservice/scssclient/ScssClientInet.py
secureclientserverservice/scssclient/ScssEchoClientInet.py
secureclientserverservice/scssclient/__init__.py
secureclientserverservice/scsscommon/ScssCommon.py
secureclientserverservice/scsscommon/ScssConfig.py
secureclientserverservice/scsscommon/__init__.py
secureclientserverservice/scsshelper/ScssClientHelper.py
secureclientserverservice/scsshelper/ScssServerHelper.py
secureclientserverservice/scsshelper/__init__.py
secureclientserverservice/scssprotocol/ScssProtocol.py
secureclientserverservice/scssprotocol/__init__.py
secureclientserverservice/scsssecurity/ScssSecurityFirewall.py
secureclientserverservice/scsssecurity/ScssSecurityHelper.py
secureclientserverservice/scsssecurity/__init__.py
secureclientserverservice/scssserver/ScssEchoServerInet.py
secureclientserverservice/scssserver/ScssServer.py
secureclientserverservice/scssserver/ScssServerInet.py
secureclientserverservice/scssserver/ScssServerUnix.py
secureclientserverservice/scssserver/__init__.py
secureclientserverservice-0.1.dist-info/LICENSE
secureclientserverservice-0.1.dist-info/METADATA
secureclientserverservice-0.1.dist-info/WHEEL
secureclientserverservice-0.1.dist-info/entry_points.txt
secureclientserverservice-0.1.dist-info/top_level.txt
secureclientserverservice-0.1.dist-info/RECORD
