Metadata-Version: 2.1
Name: secureclientserverservice
Version: 0.1
Summary: Secure client-server service library.
Home-page: https://github.com/xmzxmz
Author: Marcin Zelek
Author-email: marcin.zelek@gmail.com
License: MIT
Keywords: secure client server service
Platform: UNKNOWN
